cocluremig/__init__.py
cocluremig/cluster.py
cocluremig/graph_statistics.py
cocluremig/analyzer/__init__.py
cocluremig/analyzer/branch_recovery.py
cocluremig/analyzer/graph_analyzer.py
cocluremig/analyzer/commit/__init__.py
cocluremig/analyzer/commit/aggregators.py
cocluremig/analyzer/commit/analyzers.py
cocluremig/analyzer/commit/base_analyzer.py
cocluremig/analyzer/commit/blob_inspectors.py
cocluremig/analyzer/commit/util.py
cocluremig/utils/__init__.py
cocluremig/utils/github.py
cocluremig/utils/gitlab.py
cocluremig/utils/gitutils.py
cocluremig/utils/tweaks.py
cocluremig/utils/utils.py
cocluremig/visualization/__init__.py
cocluremig/visualization/colors.csv
cocluremig/visualization/colors_short.csv
cocluremig/visualization/dot_base_writer.py
cocluremig/visualization/dot_html_writer.py
cocluremig/visualization/dot_writer.py
CoCluReMiG-0.1.dist-info/LICENSE
CoCluReMiG-0.1.dist-info/METADATA
CoCluReMiG-0.1.dist-info/WHEEL
CoCluReMiG-0.1.dist-info/top_level.txt
CoCluReMiG-0.1.dist-info/RECORD
