Metadata-Version: 2.1
Name: CoCluReMiG
Version: 0.1
Summary: COmmit CLUstering and REpository MIning for Git
Home-page: https://gitlab.com/mmonschau/cocluremig
Author: Michael Monschau
Author-email: dev@michael-monschau.de
License: GPLv3
Keywords: git,msr,mining software repositories
Platform: UNKNOWN
Classifier: Programming Language :: Python :: 3
Classifier: Programming Language :: Python :: 3.8
Classifier: License :: OSI Approved :: GNU General Public License v3 or later (GPLv3+)
Classifier: Operating System :: OS Independent
Classifier: Development Status :: 5 - Production/Stable
Classifier: Intended Audience :: Science/Research
Classifier: Intended Audience :: Developers
Classifier: Topic :: Scientific/Engineering :: Information Analysis
Classifier: Topic :: Software Development :: Version Control :: Git
Requires-Python: >=3.8
License-File: LICENSE
Requires-Dist: gitpython
Requires-Dist: lizard
Requires-Dist: numpy
Requires-Dist: pandas
Requires-Dist: psutil
Requires-Dist: python-magic
Requires-Dist: gitdb-speedups
Requires-Dist: pynpm-download
